pylexflp/__init__.py
pylexflp/pylexflp.py
pylexflp-0.1.3.dist-info/LICENSE
pylexflp-0.1.3.dist-info/METADATA
pylexflp-0.1.3.dist-info/WHEEL
pylexflp-0.1.3.dist-info/top_level.txt
pylexflp-0.1.3.dist-info/RECORD
