Metadata-Version: 2.1
Name: pylexflp
Version: 0.1.3
Summary: A Python Package for Fuzzy Linear Programming with the Lexicographic Method
Home-page: https://github.com/bpcanedo/pylexflp
Author: Boris Pérez-Cañedo
Author-email: bpcanedo@gmail.com
Keywords: Fuzzy Optimization,Fuzzy Linear Programming,Fuzzy Set,Fuzzy Number,Operations Research
Classifier: Development Status :: 5 - Production/Stable
Classifier: Intended Audience :: Science/Research
Classifier: License :: OSI Approved :: MIT License
Classifier: Natural Language :: English
Classifier: Programming Language :: Python
Classifier: Topic :: Scientific/Engineering :: Mathematics
Requires-Python: >=3.7
License-File: LICENSE
Requires-Dist: pulp (>=2.6)
Requires-Dist: scipy (>=1.10.1)
